elmo/__about__.py
elmo/__init__.py
elmo/query.py
elmo/systems.py
elmo/utils.py
elmo/api/__init__.py
elmo/api/client.py
elmo/api/decorators.py
elmo/api/exceptions.py
elmo/api/router.py
econnect_python-0.14.1.dist-info/METADATA
econnect_python-0.14.1.dist-info/WHEEL
econnect_python-0.14.1.dist-info/licenses/LICENSE
econnect_python-0.14.1.dist-info/RECORD
