Metadata-Version: 2.4
Name: econnect-python
Version: 0.14.1
Summary: API adapter used to control programmatically an Elmo alarm system
Project-URL: Documentation, https://github.com/palazzem/econnect-python#readme
Project-URL: Issues, https://github.com/palazzem/econnect-python/issues
Project-URL: Source, https://github.com/palazzem/econnect-python
Author-email: Emanuele Palazzetti <emanuele.palazzetti@gmail.com>
License-Expression: Apache-2.0
License-File: LICENSE
Classifier: Development Status :: 4 - Beta
Classifier: Programming Language :: Python
Classifier: Programming Language :: Python :: 3.9
Classifier: Programming Language :: Python :: 3.10
Classifier: Programming Language :: Python :: 3.11
Classifier: Programming Language :: Python :: 3.12
Classifier: Programming Language :: Python :: 3.13
Classifier: Programming Language :: Python :: Implementation :: CPython
Classifier: Programming Language :: Python :: Implementation :: PyPy
Requires-Python: >=3.9
Requires-Dist: requests[security]
Provides-Extra: all
Requires-Dist: black; extra == 'all'
Requires-Dist: flake8; extra == 'all'
Requires-Dist: mypy; extra == 'all'
Requires-Dist: pre-commit; extra == 'all'
Requires-Dist: pytest; extra == 'all'
Requires-Dist: pytest-cov; extra == 'all'
Requires-Dist: pytest-mock; extra == 'all'
Requires-Dist: responses; extra == 'all'
Requires-Dist: tox; extra == 'all'
Provides-Extra: dev
Requires-Dist: mypy; extra == 'dev'
Requires-Dist: pre-commit; extra == 'dev'
Requires-Dist: pytest; extra == 'dev'
Requires-Dist: pytest-cov; extra == 'dev'
Requires-Dist: pytest-mock; extra == 'dev'
Requires-Dist: responses; extra == 'dev'
Requires-Dist: tox; extra == 'dev'
Provides-Extra: lint
Requires-Dist: black; extra == 'lint'
Requires-Dist: flake8; extra == 'lint'
